aiosmb/__init__.py
aiosmb/_version.py
aiosmb/connection.py
aiosmb/commons/__init__.py
aiosmb/commons/exceptions.py
aiosmb/commons/smbcontainer.py
aiosmb/commons/connection/__init__.py
aiosmb/commons/connection/factory.py
aiosmb/commons/connection/params.py
aiosmb/commons/connection/target.py
aiosmb/commons/interfaces/__init__.py
aiosmb/commons/interfaces/directory.py
aiosmb/commons/interfaces/domain.py
aiosmb/commons/interfaces/file.py
aiosmb/commons/interfaces/localgroup.py
aiosmb/commons/interfaces/machine.py
aiosmb/commons/interfaces/session.py
aiosmb/commons/interfaces/share.py
aiosmb/commons/interfaces/blocking/__init__.py
aiosmb/commons/interfaces/blocking/file/__init__.py
aiosmb/commons/interfaces/blocking/file/blockingfile.py
aiosmb/commons/interfaces/blocking/file/file.py
aiosmb/commons/interfaces/blocking/file/protocol.py
aiosmb/commons/scanner/__init__.py
aiosmb/commons/scanner/scanner.py
aiosmb/commons/scanner/common/__init__.py
aiosmb/commons/scanner/common/comms.py
aiosmb/commons/scanner/scanners/__init__.py
aiosmb/commons/scanner/targetgen/__init__.py
aiosmb/commons/scanner/targetgen/filetarget.py
aiosmb/commons/scanner/targetgen/listtarget.py
aiosmb/commons/utils/__init__.py
aiosmb/commons/utils/cpasswd.py
aiosmb/commons/utils/decorators.py
aiosmb/commons/utils/extb.py
aiosmb/commons/utils/faccess.py
aiosmb/commons/utils/fmtsize.py
aiosmb/commons/utils/glob2re.py
aiosmb/commons/utils/hexdump.py
aiosmb/commons/utils/ts2dt.py
aiosmb/commons/utils/univeraljson.py
aiosmb/dcerpc/__init__.py
aiosmb/dcerpc/v5/__init__.py
aiosmb/dcerpc/v5/atsvc.py
aiosmb/dcerpc/v5/bkrp.py
aiosmb/dcerpc/v5/connection.py
aiosmb/dcerpc/v5/dfsnm.py
aiosmb/dcerpc/v5/drsuapi.py
aiosmb/dcerpc/v5/dtypes.py
aiosmb/dcerpc/v5/efsr.py
aiosmb/dcerpc/v5/enum.py
aiosmb/dcerpc/v5/epm.py
aiosmb/dcerpc/v5/even.py
aiosmb/dcerpc/v5/even6.py
aiosmb/dcerpc/v5/fsrvp.py
aiosmb/dcerpc/v5/gkdi.py
aiosmb/dcerpc/v5/hresult_errors.py
aiosmb/dcerpc/v5/icpr.py
aiosmb/dcerpc/v5/lsad.py
aiosmb-0.4.13.dist-info/LICENSE.md
aiosmb-0.4.13.dist-info/METADATA
aiosmb-0.4.13.dist-info/WHEEL
aiosmb-0.4.13.dist-info/entry_points.txt
aiosmb-0.4.13.dist-info/top_level.txt
aiosmb-0.4.13.dist-info/RECORD
