Metadata-Version: 2.1
Name: aiosmb
Version: 0.4.13
Summary: Asynchronous SMB protocol implementation
Home-page: https://github.com/skelsec/aiosmb
Author: Tamas Jos
Author-email: info@skelsecprojects.com
License: Modified Apache Software License 1.1
Classifier: Programming Language :: Python :: 3.7
Classifier: Operating System :: OS Independent
Requires-Python: >=3.7
License-File: LICENSE.md
Requires-Dist: unicrypto (>=0.0.10)
Requires-Dist: asyauth (>=0.0.22)
Requires-Dist: asysocks (>=0.2.17)
Requires-Dist: prompt-toolkit (>=3.0.2)
Requires-Dist: winacl (>=0.1.9)
Requires-Dist: six
Requires-Dist: tqdm
Requires-Dist: colorama
Requires-Dist: asn1crypto
Requires-Dist: wcwidth
Requires-Dist: cryptography
